cyber_signature/__init__.py
cyber_signature/__main__.py
cyber_signature/app/__init__.py
cyber_signature/app/api/__init__.py
cyber_signature/app/api/api.py
cyber_signature/app/cli/__init__.py
cyber_signature/app/cli/app.py
cyber_signature/pdf.py
cyber_signature/signature_service.py
cyber_signature-0.1.4.dist-info/entry_points.txt
cyber_signature-0.1.4.dist-info/LICENSE
cyber_signature-0.1.4.dist-info/METADATA
cyber_signature-0.1.4.dist-info/WHEEL
cyber_signature-0.1.4.dist-info/RECORD
