Metadata-Version: 2.1
Name: cyber-signature
Version: 0.1.4
Summary: 
Author: Cristian Triana
Author-email: crisdevelop4@gmail.com
Requires-Python: >=3.9,<4.0
Classifier: Programming Language :: Python :: 3
Classifier: Programming Language :: Python :: 3.9
Classifier: Programming Language :: Python :: 3.10
Classifier: Programming Language :: Python :: 3.11
Requires-Dist: cryptography (>=41.0.1,<42.0.0)
Requires-Dist: pypdf (>=3.9.0,<4.0.0)
Requires-Dist: reportlab (>=4.0.4,<5.0.0)
Requires-Dist: typer[all] (>=0.9.0,<0.10.0)
